ext_auth/apps.py
ext_auth/choices.py
ext_auth/default_settings.py
ext_auth/keys.py
ext_auth/models.py
ext_auth/urls.py
ext_auth/views.py
ext_auth/backends/__init__.py
ext_auth/backends/ext_auth.py
ext_auth/backends/providers/__init__.py
ext_auth/backends/providers/aad.py
ext_auth/middleware/__init__.py
ext_auth/middleware/tokens.py
ext_auth/migrations/0001_initial.py
ext_auth/migrations/0002_userprofile_display_name_and_more.py
ext_auth/migrations/0003_remove_userprofile_mode.py
ext_auth/migrations/__init__.py
ext_auth/services/__init__.py
ext_auth/services/ms_graph.py
django_auth_providers-2.0.4.dist-info/METADATA
django_auth_providers-2.0.4.dist-info/WHEEL
django_auth_providers-2.0.4.dist-info/top_level.txt
django_auth_providers-2.0.4.dist-info/RECORD
