Metadata-Version: 2.1
Name: django-auth-providers
Version: 2.0.4
Summary: django-auth-providers is a django app that lets you authenticate to external authentication providers
Home-page: https://github.com/pettermoe95/django-ext-auth/tree/main
Author: Petter Elenius Moe
Author-email: pettermoe9530@gmail.com
Requires-Dist: Django>=5.1
Requires-Dist: msal>=1.31.0
Requires-Dist: djangorestframework>=3.0.0
Requires-Dist: requests>=2.32.3
